dask_elasticsearch/__init__.py
dask_elasticsearch-0.1.0.dist-info/DESCRIPTION.rst
dask_elasticsearch-0.1.0.dist-info/METADATA
dask_elasticsearch-0.1.0.dist-info/RECORD
dask_elasticsearch-0.1.0.dist-info/WHEEL
dask_elasticsearch-0.1.0.dist-info/metadata.json
dask_elasticsearch-0.1.0.dist-info/top_level.txt
