Metadata-Version: 2.0
Name: dask-elasticsearch
Version: 0.1.0
Summary: Elasticsearch reader for Dask.
Home-page: https://github.com/rolando/dask-elasticsearch
Author: Rolando (Max) Espinoza
Author-email: rolando@rmax.io
License: MIT
Keywords: dask-elasticsearch
Platform: UNKNOWN
Classifier: Development Status :: 2 - Pre-Alpha
Classifier: Intended Audience :: Developers
Classifier: License :: OSI Approved :: MIT License
Classifier: Natural Language :: English
Classifier: Programming Language :: Python :: 2
Classifier: Programming Language :: Python :: 2.7
Classifier: Programming Language :: Python :: 3
Classifier: Programming Language :: Python :: 3.4
Classifier: Programming Language :: Python :: 3.5
Requires-Dist: dask[imperative]
Requires-Dist: elasticsearch
